{"maze": [{"cell_id": 0, "word": "fake", "adjacent_to": [1, 4]}, {"cell_id": 1, "word": "wake", "adjacent_to": [0, 2]}, {"cell_id": 2, "word": "rake", "adjacent_to": [1, 3, 6]}, {"cell_id": 3, "word": "rave", "adjacent_to": [2]}, {"cell_id": 4, "word": "bake", "adjacent_to": [8, 0]}, {"cell_id": 5, "word": "wage", "adjacent_to": [6, 9]}, {"cell_id": 6, "word": "rage", "adjacent_to": [5, 2]}, {"cell_id": 7, "word": "sane", "adjacent_to": [11]}, {"cell_id": 8, "word": "cake", "adjacent_to": [12, 4]}, {"cell_id": 9, "word": "wave", "adjacent_to": [10, 13, 5]}, {"cell_id": 10, "word": "wane", "adjacent_to": [9, 11, 14]}, {"cell_id": 11, "word": "mane", "adjacent_to": [10, 7, 15]}, {"cell_id": 12, "word": "cave", "adjacent_to": [8]}, {"cell_id": 13, "word": "wade", "adjacent_to": [9]}, {"cell_id": 14, "word": "lane", "adjacent_to": [15, 10, 15]}, {"cell_id": 15, "word": "pane", "adjacent_to": [14, 11]}]}